cell_feature_data/__init__.py
cell_feature_data/constants.py
cell_feature_data/data_loader.py
cell_feature_data/logging.conf
cell_feature_data/user_input_handler.py
cell_feature_data/bin/__init__.py
cell_feature_data/bin/create_dataset.py
cell_feature_data-1.0.5.dist-info/LICENSE
cell_feature_data-1.0.5.dist-info/METADATA
cell_feature_data-1.0.5.dist-info/WHEEL
cell_feature_data-1.0.5.dist-info/entry_points.txt
cell_feature_data-1.0.5.dist-info/top_level.txt
cell_feature_data-1.0.5.dist-info/RECORD
